repype/__init__.py
repype/__main__.py
repype/batch.py
repype/benchmark.py
repype/cli.py
repype/config.py
repype/pipeline.py
repype/stage.py
repype/status.py
repype/task.py
repype/typing.py
repype/version.py
repype/textual/__init__.py
repype/textual/__main__.py
repype/textual/app.py
repype/textual/batch.py
repype/textual/confirm.py
repype/textual/demo.py
repype/textual/editor.py
repype/textual/repype.tcss
repype/textual/run.py
repype-1.0.4.dist-info/licenses/LICENSE
repype-1.0.4.dist-info/METADATA
repype-1.0.4.dist-info/WHEEL
repype-1.0.4.dist-info/top_level.txt
repype-1.0.4.dist-info/RECORD
