Metadata-Version: 2.4
Name: repype
Version: 1.0.4
Summary: Reproducible batch processing using pipelines for scientific computing.
Home-page: https://github.com/kostrykin/repype
Author: Leonid Kostrykin
Author-email: leonid.kostrykin@bioquant.uni-heidelberg.de
License: MIT
Requires-Python: >=3.9
License-File: LICENSE
Requires-Dist: dill>=0.3.2
Requires-Dist: frozendict>=2.4
Requires-Dist: mergedeep>=1.3.4
Requires-Dist: pyyaml>=6.0.1
Requires-Dist: watchdog>=4.0.2
Requires-Dist: textual[syntax]==0.76.0
Requires-Dist: pandas<3,>=2
Dynamic: author
Dynamic: author-email
Dynamic: description
Dynamic: description-content-type
Dynamic: home-page
Dynamic: license
Dynamic: license-file
Dynamic: requires-dist
Dynamic: requires-python
Dynamic: summary
